DDDHtml/__init__.py
DDDHtml/html_body.py
DDDHtml/html_document.py
DDDHtml/html_element.py
DDDHtml/html_header.py
DDDHtml/html_title.py
dddhtml-0.1.0.dist-info/METADATA
dddhtml-0.1.0.dist-info/WHEEL
dddhtml-0.1.0.dist-info/licenses/LICENSE
dddhtml-0.1.0.dist-info/RECORD
